cligenius_cli/__init__.py
cligenius_cli/__main__.py
cligenius_cli/main.py
cligenius_cli-0.0.13.dist-info/METADATA
cligenius_cli-0.0.13.dist-info/WHEEL
cligenius_cli-0.0.13.dist-info/entry_points.txt
cligenius_cli-0.0.13.dist-info/licenses/LICENSE
cligenius_cli-0.0.13.dist-info/RECORD
